annize/.pylintrc
annize/annize_cli.py
annize/asset/__init__.py
annize/asset/data.py
annize/asset/project_info.py
annize/asset/-static/annize.png
annize/asset/-static/README/de.pdf
annize/asset/-static/README/en.pdf
annize/asset/-static/mo/de/LC_MESSAGES/annize.mo
annize/asset/-static/mo/en/LC_MESSAGES/annize.mo
annize/data/__init__.py
annize/data/color.py
annize/data/container.py
annize/data/version.py
annize/features/base.py
annize/features/task.py
annize/features/files/common.py
annize/features/i18n/common.py
annize/features/i18n/gettext.py
annize/flow/__init__.py
annize/flow/run_context.py
annize/flow/runner.py
annize/fs/__init__.py
annize/fs/ext.py
annize/i18n/__init__.py
annize/object/__init__.py
annize/object/config.py
annize/project/__init__.py
annize/project/feature_loader.py
annize/project/inspector.py
annize/project/loader.py
annize/project/file_formats/__init__.py
annize/project/file_formats/xml/__init__.py
annize/project/file_formats/xml/marshaler.py
annize/project/file_formats/xml/node_representation_handlers/__init__.py
annize/project/file_formats/xml/node_representation_handlers/argument.py
annize/project/file_formats/xml/node_representation_handlers/file.py
annize/project/file_formats/xml/node_representation_handlers/ignore_unavailable_feature.py
annize/project/file_formats/xml/node_representation_handlers/object.py
annize/project/file_formats/xml/node_representation_handlers/reference.py
annize/project/file_formats/xml/node_representation_handlers/scalar_value.py
annize/project/materializer/__init__.py
annize/project/materializer/core.py
annize/project/materializer/object_factory.py
annize/project/materializer/preprocessors.py
annize/project/materializer/behaviors/__init__.py
annize/project/materializer/behaviors/argument.py
annize/project/materializer/behaviors/basket.py
annize/project/materializer/behaviors/block.py
annize/project/materializer/behaviors/feature_unavailable.py
annize/project/materializer/behaviors/reference.py
annize-7.0.6537.dist-info/METADATA
annize-7.0.6537.dist-info/WHEEL
annize-7.0.6537.dist-info/entry_points.txt
annize-7.0.6537.dist-info/top_level.txt
annize-7.0.6537.dist-info/RECORD
