Metadata-Version: 2.4
Name: annize
Version: 7.0.6537
Summary: a simple framework for task automation with focus on visual guidance and low-code
Home-page: https://pseudopolis.eu/pino/annize
Author: Josef Hahn
Author-email: annize@pseudopolis.eu
License: AGPL 3
Keywords: python task execution
Requires-Dist: hallyd~=0.9003
Requires-Dist: klovve[graphical]~=1.6
Requires-Dist: lxml~=6.0
Requires-Dist: pycountry~=24.6
Requires-Dist: pyperclip~=1.11
Dynamic: author
Dynamic: author-email
Dynamic: description
Dynamic: description-content-type
Dynamic: home-page
Dynamic: keywords
Dynamic: license
Dynamic: requires-dist
Dynamic: summary
